pypotd/__init__.py
pypotd/const.py
pypotd/data.py
pypotd-1.0.3.dist-info/LICENSE
pypotd-1.0.3.dist-info/METADATA
pypotd-1.0.3.dist-info/WHEEL
pypotd-1.0.3.dist-info/top_level.txt
pypotd-1.0.3.dist-info/RECORD
