Metadata-Version: 2.1
Name: pypotd
Version: 1.0.3
Summary: ARRIS password of the day generator
Home-page: https://github.com/MxLinux/pypotd.git
Author: Shea Ramage
Author-email: shea@vulpes.club
License: UNKNOWN
Platform: UNKNOWN
Classifier: Intended Audience :: Telecommunications Industry
Classifier: License :: OSI Approved :: MIT License
Classifier: Operating System :: OS Independent
Classifier: Programming Language :: Python :: 3
Requires-Python: >=3.7
License-File: LICENSE
Requires-Dist: pycryptodomex
